sales_report/__init__.py
sales_report/__main__.py
sales_report/sale_analyzer.py
sales_report_for_CU_from_RUslan-0.2.0.dist-info/METADATA
sales_report_for_CU_from_RUslan-0.2.0.dist-info/WHEEL
sales_report_for_CU_from_RUslan-0.2.0.dist-info/top_level.txt
sales_report_for_CU_from_RUslan-0.2.0.dist-info/RECORD
