Metadata-Version: 2.1
Name: sales-report-for-CU-from-RUslan
Version: 0.2.0
Summary: Пакет для анализа продаж и генерации отчетов
Author-email: Ruslan <r.khuseyinov@edu.centraluniversity.ru>
Requires-Dist: pandas
